{
    "_id": "5a146958cc3ca51d6712c07c",
    "user_createid": "58c7c6b8c20d99116418a797",
    "meta_name": "vw_user_expert",
    "meta_class": "users",
    "data": {
        "meta_name": "vw_user_expert",
        "title": "Эксперты",
        "meta_class": "users",
        "colmodel": [
            {
                "label": "id",
                "name": "_id",
                "key": true,
                "hidden": true
            },
            {
                "label": "E-mail",
                "name": "email"
            },
            {
                "label": "Фио",
                "name": "fio"
            },
            {
                "label": "Телефон",
                "name": "tel"
            },
            {
                "label": "Роль",
                "name": "data.role.data.name",
                "meta_ref": {
                    "meta_class": "roles",
                    "localfield": "data.role"
                }
            }
        ]
    ,
        "filter": {"or":[{
            "data#role": "5a0c145fa0b3d515742fa277"
        },{
            "data#role": "5a1442c3edadcf1d68ca1449"
        }]}},
    "created": "2017-03-14T10:23:32.897Z",
    "__v": 0,
    "this_meta_class": "meta_view"
}